thds/humenc/__init__.py
thds/humenc/py.typed
thds_humenc-1.1.20260130200317.dist-info/METADATA
thds_humenc-1.1.20260130200317.dist-info/WHEEL
thds_humenc-1.1.20260130200317.dist-info/top_level.txt
thds_humenc-1.1.20260130200317.dist-info/RECORD
