Metadata-Version: 2.4
Name: thds.humenc
Version: 1.1.20260130200317
Summary: Binary to string encoding for human readers.
Author-email: Trilliant Health <info@trillianthealth.com>
Project-URL: Repository, https://github.com/TrilliantHealth/ds-monorepo
Requires-Python: >=3.9
Requires-Dist: thds-core
Requires-Dist: wordybin>=0.2.0
